perplexity_cli/__init__.py
perplexity_cli/cli.py
perplexity_cli/api/__init__.py
perplexity_cli/api/client.py
perplexity_cli/api/endpoints.py
perplexity_cli/api/models.py
perplexity_cli/auth/__init__.py
perplexity_cli/auth/oauth_handler.py
perplexity_cli/auth/token_manager.py
perplexity_cli/formatting/__init__.py
perplexity_cli/formatting/base.py
perplexity_cli/formatting/json.py
perplexity_cli/formatting/markdown.py
perplexity_cli/formatting/plain.py
perplexity_cli/formatting/registry.py
perplexity_cli/formatting/rich.py
perplexity_cli/resources/skill.md
perplexity_cli/threads/__init__.py
perplexity_cli/threads/cache_manager.py
perplexity_cli/threads/date_parser.py
perplexity_cli/threads/exporter.py
perplexity_cli/threads/scraper.py
perplexity_cli/utils/__init__.py
perplexity_cli/utils/config.py
perplexity_cli/utils/encryption.py
perplexity_cli/utils/logging.py
perplexity_cli/utils/rate_limiter.py
perplexity_cli/utils/retry.py
perplexity_cli/utils/style_manager.py
perplexity_cli/utils/version.py
pxcli-0.4.3.dist-info/METADATA
pxcli-0.4.3.dist-info/WHEEL
pxcli-0.4.3.dist-info/entry_points.txt
pxcli-0.4.3.dist-info/top_level.txt
pxcli-0.4.3.dist-info/RECORD
