Metadata-Version: 2.4
Name: pxcli
Version: 0.4.3
Summary: A command-line interface for querying Perplexity.ai with persistent authentication
Author-email: Jamie Mills <jamie.mills@gmail.com>
License: MIT
Project-URL: Homepage, https://github.com/jamiemills/perplexity-cli
Project-URL: Repository, https://github.com/jamiemills/perplexity-cli
Project-URL: Bug Tracker, https://github.com/jamiemills/perplexity-cli/issues
Project-URL: Source Code, https://github.com/jamiemills/perplexity-cli
Keywords: cli,perplexity,ai,query,command-line
Classifier: Development Status :: 3 - Alpha
Classifier: Environment :: Console
Classifier: Intended Audience :: Developers
Classifier: License :: OSI Approved :: MIT License
Classifier: Operating System :: OS Independent
Classifier: Programming Language :: Python :: 3
Classifier: Programming Language :: Python :: 3.12
Classifier: Topic :: Internet :: WWW/HTTP
Classifier: Topic :: Software Development :: Libraries :: Python Modules
Classifier: Topic :: Utilities
Requires-Python: <3.13,>=3.12
Requires-Dist: click>=8.0
Requires-Dist: cryptography>=41.0
Requires-Dist: httpx>=0.25
Requires-Dist: websockets>=12.0
Requires-Dist: rich>=13.0
Requires-Dist: tenacity>=8.0
Requires-Dist: python-dateutil>=2.8.0
Provides-Extra: dev
Requires-Dist: pytest>=7.0; extra == "dev"
Requires-Dist: pytest-mock>=3.0; extra == "dev"
Requires-Dist: pytest-cov>=7.0; extra == "dev"
Requires-Dist: pytest-asyncio>=1.2.0; extra == "dev"
Requires-Dist: ruff>=0.1; extra == "dev"
Requires-Dist: mypy>=1.0; extra == "dev"
